uec/__init__.py
uec/__main__.py
uec/methods.py
uec/uec.py
uec/user.py
uec-1.0.1.dist-info/DESCRIPTION.rst
uec-1.0.1.dist-info/METADATA
uec-1.0.1.dist-info/RECORD
uec-1.0.1.dist-info/WHEEL
uec-1.0.1.dist-info/entry_points.txt
uec-1.0.1.dist-info/metadata.json
uec-1.0.1.dist-info/top_level.txt
